astronomer_ci/__init__.py
astronomer_ci/cli.py
astronomer_ci/dockerhub.py
astronomer_ci/exceptions.py
astronomer_ci/github.py
astronomer_e2e_test/__init__.py
astronomer_e2e_test/astronomer_e2e_test.py
astronomer_e2e_test/graphql_requests.py
astronomer_platform/__init__.py
astronomer_platform/api/__init__.py
astronomer_platform/api/client.py
astronomer_platform/api/deployments.py
astronomer_platform/api/workspaces.py
astronomer_platform/cli/__init__.py
astronomer_platform/cli/client.py
astronomer_platform/cli/deployments.py
astronomer_platform/cli/workspaces.py
astronomer_platform/features/000_auth.feature
astronomer_platform/features/001_workspace_api.feature
astronomer_platform/features/001_workspace_cli.feature
astronomer_platform/features/002_deployments_api.feature
astronomer_platform/features/002_deployments_cli.feature
astronomer_platform/features/environment.py
astronomer_platform/features/steps/auth.py
astronomer_platform/features/steps/deployments-api.py
astronomer_platform/features/steps/deployments-cli.py
astronomer_platform/features/steps/workspaces-api.py
astronomer_platform/features/steps/workspaces-cli.py
astronomer_platform/regressions/009_deployments_regression_001_api.feature
astronomer_e2e_test-0.4.0.dist-info/LICENSE
astronomer_e2e_test-0.4.0.dist-info/METADATA
astronomer_e2e_test-0.4.0.dist-info/WHEEL
astronomer_e2e_test-0.4.0.dist-info/entry_points.txt
astronomer_e2e_test-0.4.0.dist-info/RECORD
