Metadata-Version: 2.1
Name: astronomer-e2e-test
Version: 0.4.0
Summary: Astronomer scripts for internal use
License: MIT
Author: Steven Miller
Author-email: sjmiller609@gmail.com
Requires-Python: >=3.12,<4.0
Classifier: License :: OSI Approved :: MIT License
Classifier: Operating System :: Unix
Classifier: Programming Language :: Python :: 3
Classifier: Programming Language :: Python :: 3.12
Classifier: Programming Language :: Python :: 3.13
Classifier: Topic :: Software Development :: Build Tools
Requires-Dist: behave (>=1.2.6,<2.0.0)
Requires-Dist: click (>=8.1.7,<9.0.0)
Requires-Dist: gitdb2 (>=4.0.2,<5.0.0)
Requires-Dist: gitpython (>=3.1.43,<4.0.0)
Requires-Dist: graphqlclient (>=0.2.4,<0.3.0)
Requires-Dist: packaging (>=24.2,<25.0)
Requires-Dist: pexpect (>=4.9.0,<5.0.0)
Requires-Dist: pygithub (>=2.5.0,<3.0.0)
Requires-Dist: pyyaml (>=6.0.2,<7.0.0)
Requires-Dist: requests (>=2.32.3,<3.0.0)
